fixposition/__init__.py
fixposition/checksum.py
fixposition/cli.py
fixposition/gps_node.py
fixposition/parser.py
fixposition/py.typed
fixposition/receiver.py
fixposition/recorder.py
fixposition/replay.py
fixposition/test_data.py
fixposition/utils.py
fixposition/messages/__init__.py
fixposition/messages/gga.py
fixposition/messages/hdt.py
fixposition/messages/odometry.py
fixposition-0.6.2.dist-info/LICENCE
fixposition-0.6.2.dist-info/METADATA
fixposition-0.6.2.dist-info/WHEEL
fixposition-0.6.2.dist-info/entry_points.txt
fixposition-0.6.2.dist-info/top_level.txt
fixposition-0.6.2.dist-info/RECORD
