Metadata-Version: 2.1
Name: fixposition
Version: 0.6.2
Summary: Python driver for fixposition gps
Author-email: ROX Automation <jev@roxautomation.com>
License: MIT
Project-URL: Homepage, https://gitlab.com/roxautomation/components/fixposition
Classifier: Development Status :: 3 - Alpha
Classifier: Intended Audience :: Developers
Classifier: Operating System :: OS Independent
Classifier: Programming Language :: Python
Classifier: Programming Language :: Python :: 3.11
Classifier: Topic :: Software Development :: Libraries :: Python Modules
Classifier: Typing :: Typed
Requires-Python: >=3.11
License-File: LICENCE
Requires-Dist: aiomqtt
Requires-Dist: click
Requires-Dist: coloredlogs
Requires-Dist: orjson
Requires-Dist: pydantic
Requires-Dist: pydantic-settings
Requires-Dist: roxbot
Provides-Extra: ci
Requires-Dist: pylint ; extra == 'ci'
Requires-Dist: mypy ; extra == 'ci'
Requires-Dist: pytest ; extra == 'ci'
Requires-Dist: pynmea2 ; extra == 'ci'
Provides-Extra: dev
Requires-Dist: ruff ; extra == 'dev'
Requires-Dist: mypy ; extra == 'dev'
Requires-Dist: invoke ; extra == 'dev'
Requires-Dist: pre-commit ; extra == 'dev'
Requires-Dist: pylint ; extra == 'dev'
Requires-Dist: pytest ; extra == 'dev'
Requires-Dist: pytest-cov ; extra == 'dev'
Requires-Dist: pytest-asyncio ; extra == 'dev'
Requires-Dist: pynmea2 ; extra == 'dev'
Requires-Dist: rox-bridge ; extra == 'dev'
